cli_llm_man/__init__.py
cli_llm_man/cache.py
cli_llm_man/config.py
cli_llm_man/llm_interface.py
cli_llm_man/main.py
cli_llm_man/man_retriever.py
cli_llm_man/setup_alias.py
cli_llm_man_sajid_karim-0.1.0.dist-info/LICENSE
cli_llm_man_sajid_karim-0.1.0.dist-info/METADATA
cli_llm_man_sajid_karim-0.1.0.dist-info/WHEEL
cli_llm_man_sajid_karim-0.1.0.dist-info/entry_points.txt
cli_llm_man_sajid_karim-0.1.0.dist-info/top_level.txt
cli_llm_man_sajid_karim-0.1.0.dist-info/RECORD
